hrm_recorder/__init__.py
hrm_recorder/cli.py
hrm_recorder/config.py
hrm_recorder/recorder.py
hrm_recorder-1.0.0.dist-info/METADATA
hrm_recorder-1.0.0.dist-info/WHEEL
hrm_recorder-1.0.0.dist-info/entry_points.txt
hrm_recorder-1.0.0.dist-info/top_level.txt
hrm_recorder-1.0.0.dist-info/RECORD
