Metadata-Version: 2.4
Name: hrm-recorder
Version: 1.0.0
Summary: A Python-based BLE heart rate monitor recorder using Bleak
Author-email: Gordon Dodwell <gcdodwell@gmail.com>
Project-URL: Homepage, https://github.com/Cortexan/hrm_recorder
Project-URL: Repository, https://github.com/Cortexan/hrm_recorder
Project-URL: Issues, https://github.com/Cortexan/hrm_recorder
Requires-Python: >=3.9
Requires-Dist: bleak>=0.20
